data/manip/Vacuum_Infos.json
data/manip/Vacuum_Pressure.tsv
data/manip/Vacuum_SourceBath.tsv
data/manip/Vacuum_Temperature.tsv
data/untracked_data/Pressure_resampled_1.tsv
data/untracked_data/Pressure_resampled_2.tsv
prevo/__init__.py
prevo/csv.py
prevo/measurements.py
prevo/misc.py
prevo/parser.py
prevo/control/__init__.py
prevo/control/control.py
prevo/control/program.py
prevo/plot/__init__.py
prevo/plot/general.py
prevo/plot/oscillo.py
prevo/plot/plot.py
prevo/record/__init__.py
prevo/record/general.py
prevo/record/images.py
prevo/record/numerical.py
prevo/viewers/__init__.py
prevo/viewers/general.py
prevo/viewers/matplotlib.py
prevo/viewers/opencv.py
prevo/viewers/tkinter.py
prevo-0.20.1.dist-info/licenses/LICENSE
tests/test_csv.py
tests/test_measurements.py
prevo-0.20.1.dist-info/METADATA
prevo-0.20.1.dist-info/WHEEL
prevo-0.20.1.dist-info/top_level.txt
prevo-0.20.1.dist-info/RECORD
