Metadata-Version: 2.4
Name: prevo
Version: 0.20.1
Summary: Record arbitrary sensors periodically in an asynchronous manner. Control their properties in real time from CLI. Graph/view tools to visualize live data/images are also provided.
Author-email: Olivier Vincent <ovinc.py@gmail.com>
License: GNU GPLv3
Project-URL: Homepage, https://github.com/ovinc/prevo
Project-URL: Documentation, https://github.com/ovinc/prevo/README.md
Project-URL: Repository, https://github.com/ovinc/prevo.git
Keywords: periodic,recording,data
Classifier: Programming Language :: Python :: 3
Classifier: Operating System :: OS Independent
Classifier: License :: OSI Approved :: GNU General Public License v3 or later (GPLv3+)
Requires-Python: >=3.6
License-File: LICENSE
Requires-Dist: tqdm
Requires-Dist: oclock>=1.3.2
Requires-Dist: tzlocal<3.0
Requires-Dist: clivo>=0.4.0
Requires-Dist: gittools>=0.6.0
Requires-Dist: matplotlib>=3.1
Requires-Dist: numpy
Requires-Dist: importlib-metadata
Dynamic: license-file
